{
  "id": "947b463d-fc95-4ec8-8634-34942b7b3abc",
  "prevId": "45609f27-07e5-46ea-a66d-2700151db6ce",
  "version": "5",
  "dialect": "pg",
  "tables": {
    "collections": {
      "name": "collections",
      "schema": "",
      "columns": {
        "collection_id": {
          "name": "collection_id",
          "type": "varchar",
          "primaryKey": true,
          "notNull": true
        },
        "start": {
          "name": "start",
          "type": "timestamp",
          "primaryKey": false,
          "notNull": true
        },
        "complete": {
          "name": "complete",
          "type": "timestamp",
          "primaryKey": false,
          "notNull": true
        },
        "url": {
          "name": "url",
          "type": "varchar",
          "primaryKey": false,
          "notNull": true
        },
        "status": {
          "name": "status",
          "type": "varchar",
          "primaryKey": false,
          "notNull": true
        },
        "notes": {
          "name": "notes",
          "type": "text",
          "primaryKey": false,
          "notNull": false
        },
        "errors": {
          "name": "errors",
          "type": "text",
          "primaryKey": false,
          "notNull": false
        },
        "created_at": {
          "name": "created_at",
          "type": "timestamp",
          "primaryKey": false,
          "notNull": false,
          "default": "now()"
        },
        "modified_at": {
          "name": "modified_at",
          "type": "timestamp",
          "primaryKey": false,
          "notNull": false,
          "default": "now()"
        }
      },
      "indexes": {
        "start_index": {
          "name": "start_index",
          "columns": [
            "start"
          ],
          "isUnique": false
        },
        "complete_index": {
          "name": "complete_index",
          "columns": [
            "complete"
          ],
          "isUnique": false
        },
        "status_index": {
          "name": "status_index",
          "columns": [
            "status"
          ],
          "isUnique": false
        }
      },
      "foreignKeys": {},
      "compositePrimaryKeys": {},
      "uniqueConstraints": {
        "collections_start_unique": {
          "name": "collections_start_unique",
          "nullsNotDistinct": false,
          "columns": [
            "start"
          ]
        },
        "collections_complete_unique": {
          "name": "collections_complete_unique",
          "nullsNotDistinct": false,
          "columns": [
            "complete"
          ]
        }
      }
    },
    "files": {
      "name": "files",
      "schema": "",
      "columns": {
        "file_id": {
          "name": "file_id",
          "type": "varchar",
          "primaryKey": true,
          "notNull": true
        },
        "file_name": {
          "name": "file_name",
          "type": "varchar",
          "primaryKey": false,
          "notNull": false
        },
        "fiscal_year": {
          "name": "fiscal_year",
          "type": "integer",
          "primaryKey": false,
          "notNull": false
        },
        "approval_timestamp": {
          "name": "approval_timestamp",
          "type": "timestamp",
          "primaryKey": false,
          "notNull": false
        },
        "folder": {
          "name": "folder",
          "type": "varchar",
          "primaryKey": false,
          "notNull": false
        },
        "approver_title": {
          "name": "approver_title",
          "type": "varchar",
          "primaryKey": false,
          "notNull": false
        },
        "funds_provided_by": {
          "name": "funds_provided_by",
          "type": "varchar",
          "primaryKey": false,
          "notNull": false
        },
        "excel_url": {
          "name": "excel_url",
          "type": "varchar",
          "primaryKey": false,
          "notNull": false
        },
        "pdf_url": {
          "name": "pdf_url",
          "type": "varchar",
          "primaryKey": false,
          "notNull": false
        },
        "source_url": {
          "name": "source_url",
          "type": "varchar",
          "primaryKey": false,
          "notNull": true
        },
        "source_data": {
          "name": "source_data",
          "type": "text",
          "primaryKey": false,
          "notNull": false
        },
        "created_at": {
          "name": "created_at",
          "type": "timestamp",
          "primaryKey": false,
          "notNull": false,
          "default": "now()"
        },
        "modified_at": {
          "name": "modified_at",
          "type": "timestamp",
          "primaryKey": false,
          "notNull": false,
          "default": "now()"
        },
        "removed": {
          "name": "removed",
          "type": "boolean",
          "primaryKey": false,
          "notNull": false,
          "default": false
        }
      },
      "indexes": {
        "file_name_index": {
          "name": "file_name_index",
          "columns": [
            "file_name"
          ],
          "isUnique": false
        },
        "fiscal_year_index": {
          "name": "fiscal_year_index",
          "columns": [
            "fiscal_year"
          ],
          "isUnique": false
        },
        "approval_timestamp_index": {
          "name": "approval_timestamp_index",
          "columns": [
            "approval_timestamp"
          ],
          "isUnique": false
        },
        "folder_index": {
          "name": "folder_index",
          "columns": [
            "folder"
          ],
          "isUnique": false
        },
        "approver_title_index": {
          "name": "approver_title_index",
          "columns": [
            "approver_title"
          ],
          "isUnique": false
        },
        "funds_provided_by_index": {
          "name": "funds_provided_by_index",
          "columns": [
            "funds_provided_by"
          ],
          "isUnique": false
        },
        "removed_index": {
          "name": "removed_index",
          "columns": [
            "removed"
          ],
          "isUnique": false
        }
      },
      "foreignKeys": {},
      "compositePrimaryKeys": {},
      "uniqueConstraints": {}
    },
    "footnotes": {
      "name": "footnotes",
      "schema": "",
      "columns": {
        "file_id": {
          "name": "file_id",
          "type": "varchar",
          "primaryKey": false,
          "notNull": false
        },
        "schedule_index": {
          "name": "schedule_index",
          "type": "integer",
          "primaryKey": false,
          "notNull": false
        },
        "footnote_number": {
          "name": "footnote_number",
          "type": "varchar",
          "primaryKey": false,
          "notNull": true
        },
        "footnote_text": {
          "name": "footnote_text",
          "type": "text",
          "primaryKey": false,
          "notNull": true
        },
        "created_at": {
          "name": "created_at",
          "type": "timestamp",
          "primaryKey": false,
          "notNull": false,
          "default": "now()"
        },
        "modified_at": {
          "name": "modified_at",
          "type": "timestamp",
          "primaryKey": false,
          "notNull": false,
          "default": "now()"
        }
      },
      "indexes": {
        "file_footnote_index": {
          "name": "file_footnote_index",
          "columns": [
            "file_id",
            "footnote_number"
          ],
          "isUnique": false
        }
      },
      "foreignKeys": {
        "footnotes_file_id_files_file_id_fk": {
          "name": "footnotes_file_id_files_file_id_fk",
          "tableFrom": "footnotes",
          "tableTo": "files",
          "columnsFrom": [
            "file_id"
          ],
          "columnsTo": [
            "file_id"
          ],
          "onDelete": "no action",
          "onUpdate": "no action"
        },
        "footnotes_file_id_schedule_index_schedules_file_id_schedule_index_fk": {
          "name": "footnotes_file_id_schedule_index_schedules_file_id_schedule_index_fk",
          "tableFrom": "footnotes",
          "tableTo": "schedules",
          "columnsFrom": [
            "file_id",
            "schedule_index"
          ],
          "columnsTo": [
            "file_id",
            "schedule_index"
          ],
          "onDelete": "no action",
          "onUpdate": "no action"
        }
      },
      "compositePrimaryKeys": {
        "footnotes_file_id_schedule_index_footnote_number_pk": {
          "name": "footnotes_file_id_schedule_index_footnote_number_pk",
          "columns": [
            "file_id",
            "schedule_index",
            "footnote_number"
          ]
        }
      },
      "uniqueConstraints": {}
    },
    "schedules": {
      "name": "schedules",
      "schema": "",
      "columns": {
        "file_id": {
          "name": "file_id",
          "type": "varchar",
          "primaryKey": false,
          "notNull": false
        },
        "schedule_index": {
          "name": "schedule_index",
          "type": "integer",
          "primaryKey": false,
          "notNull": false,
          "default": 0
        },
        "budget_agency_title": {
          "name": "budget_agency_title",
          "type": "varchar",
          "primaryKey": false,
          "notNull": false
        },
        "budget_bureau_title": {
          "name": "budget_bureau_title",
          "type": "varchar",
          "primaryKey": false,
          "notNull": false
        },
        "account_title": {
          "name": "account_title",
          "type": "varchar",
          "primaryKey": false,
          "notNull": false
        },
        "allocation_agency_code": {
          "name": "allocation_agency_code",
          "type": "varchar",
          "primaryKey": false,
          "notNull": false
        },
        "cgac_agency": {
          "name": "cgac_agency",
          "type": "varchar",
          "primaryKey": false,
          "notNull": false
        },
        "begin_poa": {
          "name": "begin_poa",
          "type": "integer",
          "primaryKey": false,
          "notNull": false
        },
        "end_poa": {
          "name": "end_poa",
          "type": "integer",
          "primaryKey": false,
          "notNull": false
        },
        "availability_type_code": {
          "name": "availability_type_code",
          "type": "varchar",
          "primaryKey": false,
          "notNull": false
        },
        "cgac_acct": {
          "name": "cgac_acct",
          "type": "varchar",
          "primaryKey": false,
          "notNull": false
        },
        "allocation_subacct": {
          "name": "allocation_subacct",
          "type": "varchar",
          "primaryKey": false,
          "notNull": false
        },
        "iteration": {
          "name": "iteration",
          "type": "integer",
          "primaryKey": false,
          "notNull": false
        },
        "tafs_iteration_id": {
          "name": "tafs_iteration_id",
          "type": "varchar",
          "primaryKey": false,
          "notNull": false
        },
        "line_number": {
          "name": "line_number",
          "type": "varchar",
          "primaryKey": false,
          "notNull": false
        },
        "line_split": {
          "name": "line_split",
          "type": "varchar",
          "primaryKey": false,
          "notNull": false
        },
        "line_description": {
          "name": "line_description",
          "type": "varchar",
          "primaryKey": false,
          "notNull": false
        },
        "approved_amount": {
          "name": "approved_amount",
          "type": "bigint",
          "primaryKey": false,
          "notNull": false
        },
        "created_at": {
          "name": "created_at",
          "type": "timestamp",
          "primaryKey": false,
          "notNull": false,
          "default": "now()"
        },
        "modified_at": {
          "name": "modified_at",
          "type": "timestamp",
          "primaryKey": false,
          "notNull": false,
          "default": "now()"
        }
      },
      "indexes": {
        "budget_agency_title_index": {
          "name": "budget_agency_title_index",
          "columns": [
            "budget_agency_title"
          ],
          "isUnique": false
        },
        "budget_bureau_title_index": {
          "name": "budget_bureau_title_index",
          "columns": [
            "budget_bureau_title"
          ],
          "isUnique": false
        },
        "account_title_index": {
          "name": "account_title_index",
          "columns": [
            "account_title"
          ],
          "isUnique": false
        },
        "allocation_agency_code_index": {
          "name": "allocation_agency_code_index",
          "columns": [
            "allocation_agency_code"
          ],
          "isUnique": false
        },
        "cgac_agency_index": {
          "name": "cgac_agency_index",
          "columns": [
            "cgac_agency"
          ],
          "isUnique": false
        },
        "approved_amount_index": {
          "name": "approved_amount_index",
          "columns": [
            "approved_amount"
          ],
          "isUnique": false
        }
      },
      "foreignKeys": {
        "schedules_file_id_files_file_id_fk": {
          "name": "schedules_file_id_files_file_id_fk",
          "tableFrom": "schedules",
          "tableTo": "files",
          "columnsFrom": [
            "file_id"
          ],
          "columnsTo": [
            "file_id"
          ],
          "onDelete": "no action",
          "onUpdate": "no action"
        }
      },
      "compositePrimaryKeys": {
        "schedules_file_id_schedule_index_pk": {
          "name": "schedules_file_id_schedule_index_pk",
          "columns": [
            "file_id",
            "schedule_index"
          ]
        }
      },
      "uniqueConstraints": {}
    }
  },
  "enums": {},
  "schemas": {},
  "_meta": {
    "columns": {},
    "schemas": {},
    "tables": {}
  }
}